anal/__init__.py
anal/anal.py
anal-1.3.0.dist-info/LICENSE
anal-1.3.0.dist-info/METADATA
anal-1.3.0.dist-info/WHEEL
anal-1.3.0.dist-info/top_level.txt
anal-1.3.0.dist-info/RECORD
