Metadata-Version: 2.1
Name: anal
Version: 1.3.0
Summary: UNKNOWN
Home-page: https://github.com/averak/anal
Author: Tatsuya Abe
Author-email: abe12@mccc.jp
License: MIT
Keywords: stdout
Platform: UNKNOWN
Classifier: License :: OSI Approved :: MIT License
Classifier: Programming Language :: Python :: 3.8
